meshinfer/__init__.py
meshinfer/ops/__init__.py
meshinfer/ops/meshgemm.py
meshinfer/ops/meshgemv.py
meshinfer-0.1.2.data/data/requirements.txt
meshinfer-0.1.2.dist-info/METADATA
meshinfer-0.1.2.dist-info/WHEEL
meshinfer-0.1.2.dist-info/top_level.txt
meshinfer-0.1.2.dist-info/RECORD
